Metadata-Version: 2.1
Name: compiler-identification
Version: 1.0.3
Summary: Identifying the properties of a C/C++ compiler, such as type and version
Home-page: https://github.com/yugabyte/compiler-identification
Author: Mikhail Bautin
Author-email: mbautin@users.noreply.github.com
License: UNKNOWN
Platform: UNKNOWN
Classifier: Programming Language :: Python :: 3
Classifier: License :: OSI Approved :: Apache Software License
Classifier: Operating System :: OS Independent
Requires-Python: >=3.6
Provides-Extra: dev
